{"GlobalPropertiesHash":"jzuGwAY4KSLf4b+4lZJC4JftjE8ohj4S0uVJPFLiCys=","FingerprintPatternsHash":"gq3WsqcKBUGTSNle7RKKyXRIwh7M8ccEqOqYvIzoM04=","PropertyOverridesHash":"8ZRc1sGeVrPBx4lD717BgRaQekyh78QKV9SKsdt638U=","InputHashes":["MFT3l6GyCdJO51JPmyvtEDGlkNcfuYBTBNly1yei\u002BSY=","wNrLLcPFQoDPOfn\u002BwuJghcP6sXzGEQ8/sf\u002Bj9v2Ireo=","j0VdZMpd7wJHE72HPJvngi0gQiaCW5rdeHEkL/qOq8A=","R7D1VOK5xmYbgJGLk5UTUB6oaOhKpgSL1U9d9G0siQQ=","7Iu0ONx7T71h7/mhey4EqArOv9SWsm56oqsOpr6/AvU=","\u002Bt88g0YoVRWisP3N4\u002B37ilup3U\u002Bo6TusvuWZ6fv9CeM=","1eN1gNxCxokSAI1cQDwTlqnnA4FTVxbPzDL2gNcB2JE=","av1\u002ByWqMUSQMtiCl8O3ogFHdTIPEbO8CaQf7WvEYW2s=","ect7RaUPSBQHivPtzIKwAuO21gs7E1O8o4XF2PzlFzU=","isYcWUirWLR3fNti5OcSTqkJvi7gIxRyNG85lZkJASI=","DoFJCTnP6lvLkU1hNqFIIbXCECI9XDCQM1L7E5UlKfs=","gi4cwoT00EaWLfE9LJLoVWx2\u002Bx/RmJzRTfx678BCt24=","jHKAMTm3yb3qjuSh8I392NHPJ4740RvNAsmR0yEv/98=","TOVcqs2h6pQqp5ux9944WUNcfSa8Lh9sniJpEMjSt44=","fjoS1i3PtuFri\u002Bhcp\u002BGQRSPkN2K/jI2BFTzldkUdQHA=","ox04cOq5upXtg4gC6EoXSwgpXkGyL7M5DewKmJuOMDs=","x7hv7HtURuKBsng958yqD6YaSAbCBMhWL/l5q0vBmq4=","eBDjFuoUKhXcm2pqRosLoEWZO8Hdpgs/tl3IHoy4NJM=","Mo8pPx1h27VQ8zcNVlC2\u002BdCDZIUr6majkCRTYoeuZfw=","JPghgqVdorh1L64AiHbZN\u002B0TooNrZvMz5/lX/lmfsL8=","lDw/Zoqaz4OHqBv9A\u002B05WGvcXaJ3RUaejXrhrIfaadA=","XZNYH7gPvweXKOtJsDLgR97/O9KHNZnYnQtAGjP0r/o=","yvQFXCHeHwjsq5Mp9WYK6ARHxJdpokqg9V/KwijvBbw=","8HVUdh8eSFxdZFDkzjGROPpSRtFc\u002BwTCoGDPtr\u002BnYQk=","i7CZm\u002BiHXK1N\u002BQxOBCKNWJwAG7VYGrcgAPGcLQ4MZ5Q=","cALyj8dc7LEuLLrvpmJEJQqxWRrB55nPNbd1uaqVfu4=","Z7Ajx\u002B4htCQ4Nr6gc4Q4BMnk4b9\u002B47ECVrocxDIAjj0="],"CachedAssets":{"MFT3l6GyCdJO51JPmyvtEDGlkNcfuYBTBNly1yei\u002BSY=":{"Identity":"C:\\Users\\helen\\OneDrive\\Desktop\\Disney_ShowDown\\DisneyShowdown\\wwwroot\\css\\bootstrap\\bootstrap.min.css","SourceId":"DisneyShowdown","SourceType":"Discovered","ContentRoot":"C:\\Users\\helen\\OneDrive\\Desktop\\Disney_ShowDown\\DisneyShowdown\\wwwroot\\","BasePath":"_content/DisneyShowdown","RelativePath":"css/bootstrap/bootstrap.min#[.{fingerprint}]?.css","AssetKind":"All","AssetMode":"All","AssetRole":"Primary","AssetMergeBehavior":null,"AssetMergeSource":"","RelatedAsset":null,"AssetTraitName":null,"AssetTraitValue":null,"Fingerprint":"bpk8xqwxhs","Integrity":"z8OR40MowJ8GgK6P89Y\u002BhiJK5\u002BcclzFHzLhFQLL92bg=","CopyToOutputDirectory":"Never","CopyToPublishDirectory":"PreserveNewest","OriginalItemSpec":"wwwroot\\css\\bootstrap\\bootstrap.min.css","FileLength":162720,"LastWriteTime":"2025-08-11T17:18:34.9802119+00:00"},"wNrLLcPFQoDPOfn\u002BwuJghcP6sXzGEQ8/sf\u002Bj9v2Ireo=":{"Identity":"C:\\Users\\helen\\OneDrive\\Desktop\\Disney_ShowDown\\DisneyShowdown\\wwwroot\\css\\bootstrap\\bootstrap.min.css.map","SourceId":"DisneyShowdown","SourceType":"Discovered","ContentRoot":"C:\\Users\\helen\\OneDrive\\Desktop\\Disney_ShowDown\\DisneyShowdown\\wwwroot\\","BasePath":"_content/DisneyShowdown","RelativePath":"css/bootstrap/bootstrap.min.css#[.{fingerprint}]?.map","AssetKind":"All","AssetMode":"All","AssetRole":"Primary","AssetMergeBehavior":null,"AssetMergeSource":"","RelatedAsset":null,"AssetTraitName":null,"AssetTraitValue":null,"Fingerprint":"8inm30yfxf","Integrity":"gBwg2tmA0Ci2u54gMF1jNCVku6vznarkLS6D76htNNQ=","CopyToOutputDirectory":"Never","CopyToPublishDirectory":"PreserveNewest","OriginalItemSpec":"wwwroot\\css\\bootstrap\\bootstrap.min.css.map","FileLength":449111,"LastWriteTime":"2025-08-11T17:18:34.9802119+00:00"},"j0VdZMpd7wJHE72HPJvngi0gQiaCW5rdeHEkL/qOq8A=":{"Identity":"C:\\Users\\helen\\OneDrive\\Desktop\\Disney_ShowDown\\DisneyShowdown\\wwwroot\\css\\open-iconic\\FONT-LICENSE","SourceId":"DisneyShowdown","SourceType":"Discovered","ContentRoot":"C:\\Users\\helen\\OneDrive\\Desktop\\Disney_ShowDown\\DisneyShowdown\\wwwroot\\","BasePath":"_content/DisneyShowdown","RelativePath":"css/open-iconic/FONT-LICENSE#[.{fingerprint}]?","AssetKind":"All","AssetMode":"All","AssetRole":"Primary","AssetMergeBehavior":null,"AssetMergeSource":"","RelatedAsset":null,"AssetTraitName":null,"AssetTraitValue":null,"Fingerprint":"48tmkg660f","Integrity":"jA4J4h/k76zVxbFKEaWwFKJccmO0voOQ1DbUW\u002B5YNlI=","CopyToOutputDirectory":"Never","CopyToPublishDirectory":"PreserveNewest","OriginalItemSpec":"wwwroot\\css\\open-iconic\\FONT-LICENSE","FileLength":4103,"LastWriteTime":"2025-08-11T17:18:34.9822147+00:00"},"R7D1VOK5xmYbgJGLk5UTUB6oaOhKpgSL1U9d9G0siQQ=":{"Identity":"C:\\Users\\helen\\OneDrive\\Desktop\\Disney_ShowDown\\DisneyShowdown\\wwwroot\\css\\open-iconic\\font\\css\\open-iconic-bootstrap.min.css","SourceId":"DisneyShowdown","SourceType":"Discovered","ContentRoot":"C:\\Users\\helen\\OneDrive\\Desktop\\Disney_ShowDown\\DisneyShowdown\\wwwroot\\","BasePath":"_content/DisneyShowdown","RelativePath":"css/open-iconic/font/css/open-iconic-bootstrap.min#[.{fingerprint}]?.css","AssetKind":"All","AssetMode":"All","AssetRole":"Primary","AssetMergeBehavior":null,"AssetMergeSource":"","RelatedAsset":null,"AssetTraitName":null,"AssetTraitValue":null,"Fingerprint":"cmapd0fi15","Integrity":"BJ/G\u002Be\u002By7bQdrYkS2RBTyNfBHpA9IuGaPmf9htub5MQ=","CopyToOutputDirectory":"Never","CopyToPublishDirectory":"PreserveNewest","OriginalItemSpec":"wwwroot\\css\\open-iconic\\font\\css\\open-iconic-bootstrap.min.css","FileLength":9395,"LastWriteTime":"2025-08-11T17:18:34.8881454+00:00"},"7Iu0ONx7T71h7/mhey4EqArOv9SWsm56oqsOpr6/AvU=":{"Identity":"C:\\Users\\helen\\OneDrive\\Desktop\\Disney_ShowDown\\DisneyShowdown\\wwwroot\\css\\open-iconic\\font\\fonts\\open-iconic.eot","SourceId":"DisneyShowdown","SourceType":"Discovered","ContentRoot":"C:\\Users\\helen\\OneDrive\\Desktop\\Disney_ShowDown\\DisneyShowdown\\wwwroot\\","BasePath":"_content/DisneyShowdown","RelativePath":"css/open-iconic/font/fonts/open-iconic#[.{fingerprint}]?.eot","AssetKind":"All","AssetMode":"All","AssetRole":"Primary","AssetMergeBehavior":null,"AssetMergeSource":"","RelatedAsset":null,"AssetTraitName":null,"AssetTraitValue":null,"Fingerprint":"0uw8dim9nl","Integrity":"OK3poGPgzKI2NzNgP07XMbJa3Dz6USoUh/chSkSvQpc=","CopyToOutputDirectory":"Never","CopyToPublishDirectory":"PreserveNewest","OriginalItemSpec":"wwwroot\\css\\open-iconic\\font\\fonts\\open-iconic.eot","FileLength":28196,"LastWriteTime":"2025-08-11T17:18:34.8881454+00:00"},"\u002Bt88g0YoVRWisP3N4\u002B37ilup3U\u002Bo6TusvuWZ6fv9CeM=":{"Identity":"C:\\Users\\helen\\OneDrive\\Desktop\\Disney_ShowDown\\DisneyShowdown\\wwwroot\\css\\open-iconic\\font\\fonts\\open-iconic.otf","SourceId":"DisneyShowdown","SourceType":"Discovered","ContentRoot":"C:\\Users\\helen\\OneDrive\\Desktop\\Disney_ShowDown\\DisneyShowdown\\wwwroot\\","BasePath":"_content/DisneyShowdown","RelativePath":"css/open-iconic/font/fonts/open-iconic#[.{fingerprint}]?.otf","AssetKind":"All","AssetMode":"All","AssetRole":"Primary","AssetMergeBehavior":null,"AssetMergeSource":"","RelatedAsset":null,"AssetTraitName":null,"AssetTraitValue":null,"Fingerprint":"wk8x8xm0ah","Integrity":"sDUtuZAEzWZyv/U1xl/9D3ehyU69JE\u002BFvAcu5HQ\u002B/a0=","CopyToOutputDirectory":"Never","CopyToPublishDirectory":"PreserveNewest","OriginalItemSpec":"wwwroot\\css\\open-iconic\\font\\fonts\\open-iconic.otf","FileLength":20996,"LastWriteTime":"2025-08-11T17:18:34.8947412+00:00"},"1eN1gNxCxokSAI1cQDwTlqnnA4FTVxbPzDL2gNcB2JE=":{"Identity":"C:\\Users\\helen\\OneDrive\\Desktop\\Disney_ShowDown\\DisneyShowdown\\wwwroot\\css\\open-iconic\\font\\fonts\\open-iconic.svg","SourceId":"DisneyShowdown","SourceType":"Discovered","ContentRoot":"C:\\Users\\helen\\OneDrive\\Desktop\\Disney_ShowDown\\DisneyShowdown\\wwwroot\\","BasePath":"_content/DisneyShowdown","RelativePath":"css/open-iconic/font/fonts/open-iconic#[.{fingerprint}]?.svg","AssetKind":"All","AssetMode":"All","AssetRole":"Primary","AssetMergeBehavior":null,"AssetMergeSource":"","RelatedAsset":null,"AssetTraitName":null,"AssetTraitValue":null,"Fingerprint":"sjnzgf7e1h","Integrity":"\u002BP1oQ5jPzOVJGC52E1oxGXIXxxCyMlqy6A9cNxGYzVk=","CopyToOutputDirectory":"Never","CopyToPublishDirectory":"PreserveNewest","OriginalItemSpec":"wwwroot\\css\\open-iconic\\font\\fonts\\open-iconic.svg","FileLength":55332,"LastWriteTime":"2025-08-11T17:18:34.8947412+00:00"},"av1\u002ByWqMUSQMtiCl8O3ogFHdTIPEbO8CaQf7WvEYW2s=":{"Identity":"C:\\Users\\helen\\OneDrive\\Desktop\\Disney_ShowDown\\DisneyShowdown\\wwwroot\\css\\open-iconic\\font\\fonts\\open-iconic.ttf","SourceId":"DisneyShowdown","SourceType":"Discovered","ContentRoot":"C:\\Users\\helen\\OneDrive\\Desktop\\Disney_ShowDown\\DisneyShowdown\\wwwroot\\","BasePath":"_content/DisneyShowdown","RelativePath":"css/open-iconic/font/fonts/open-iconic#[.{fingerprint}]?.ttf","AssetKind":"All","AssetMode":"All","AssetRole":"Primary","AssetMergeBehavior":null,"AssetMergeSource":"","RelatedAsset":null,"AssetTraitName":null,"AssetTraitValue":null,"Fingerprint":"ll5grcv8wv","Integrity":"p\u002BRP8CV3vRK1YbIkNzq3rPo1jyETPnR07ULb\u002BHVYL8w=","CopyToOutputDirectory":"Never","CopyToPublishDirectory":"PreserveNewest","OriginalItemSpec":"wwwroot\\css\\open-iconic\\font\\fonts\\open-iconic.ttf","FileLength":28028,"LastWriteTime":"2025-08-11T17:18:34.8947412+00:00"},"ect7RaUPSBQHivPtzIKwAuO21gs7E1O8o4XF2PzlFzU=":{"Identity":"C:\\Users\\helen\\OneDrive\\Desktop\\Disney_ShowDown\\DisneyShowdown\\wwwroot\\css\\open-iconic\\font\\fonts\\open-iconic.woff","SourceId":"DisneyShowdown","SourceType":"Discovered","ContentRoot":"C:\\Users\\helen\\OneDrive\\Desktop\\Disney_ShowDown\\DisneyShowdown\\wwwroot\\","BasePath":"_content/DisneyShowdown","RelativePath":"css/open-iconic/font/fonts/open-iconic#[.{fingerprint}]?.woff","AssetKind":"All","AssetMode":"All","AssetRole":"Primary","AssetMergeBehavior":null,"AssetMergeSource":"","RelatedAsset":null,"AssetTraitName":null,"AssetTraitValue":null,"Fingerprint":"h4d0pazwgy","Integrity":"cZPqVlRJfSNW0KaQ4\u002BUPOXZ/v/QzXlejRDwUNdZIofI=","CopyToOutputDirectory":"Never","CopyToPublishDirectory":"PreserveNewest","OriginalItemSpec":"wwwroot\\css\\open-iconic\\font\\fonts\\open-iconic.woff","FileLength":14984,"LastWriteTime":"2025-08-11T17:18:34.8967442+00:00"},"isYcWUirWLR3fNti5OcSTqkJvi7gIxRyNG85lZkJASI=":{"Identity":"C:\\Users\\helen\\OneDrive\\Desktop\\Disney_ShowDown\\DisneyShowdown\\wwwroot\\css\\open-iconic\\ICON-LICENSE","SourceId":"DisneyShowdown","SourceType":"Discovered","ContentRoot":"C:\\Users\\helen\\OneDrive\\Desktop\\Disney_ShowDown\\DisneyShowdown\\wwwroot\\","BasePath":"_content/DisneyShowdown","RelativePath":"css/open-iconic/ICON-LICENSE#[.{fingerprint}]?","AssetKind":"All","AssetMode":"All","AssetRole":"Primary","AssetMergeBehavior":null,"AssetMergeSource":"","RelatedAsset":null,"AssetTraitName":null,"AssetTraitValue":null,"Fingerprint":"4dwjve0o0b","Integrity":"aF5g/izareSj02F3MPSoTGNbcMBl9nmZKDe04zjU/ss=","CopyToOutputDirectory":"Never","CopyToPublishDirectory":"PreserveNewest","OriginalItemSpec":"wwwroot\\css\\open-iconic\\ICON-LICENSE","FileLength":1093,"LastWriteTime":"2025-08-11T17:18:34.9827182+00:00"},"DoFJCTnP6lvLkU1hNqFIIbXCECI9XDCQM1L7E5UlKfs=":{"Identity":"C:\\Users\\helen\\OneDrive\\Desktop\\Disney_ShowDown\\DisneyShowdown\\wwwroot\\css\\open-iconic\\README.md","SourceId":"DisneyShowdown","SourceType":"Discovered","ContentRoot":"C:\\Users\\helen\\OneDrive\\Desktop\\Disney_ShowDown\\DisneyShowdown\\wwwroot\\","BasePath":"_content/DisneyShowdown","RelativePath":"css/open-iconic/README#[.{fingerprint}]?.md","AssetKind":"All","AssetMode":"All","AssetRole":"Primary","AssetMergeBehavior":null,"AssetMergeSource":"","RelatedAsset":null,"AssetTraitName":null,"AssetTraitValue":null,"Fingerprint":"5bzwdl5l6x","Integrity":"waukoLqsiIAw/nXpsKkTHnhImmcPijcBEd2lzqzJNN0=","CopyToOutputDirectory":"Never","CopyToPublishDirectory":"PreserveNewest","OriginalItemSpec":"wwwroot\\css\\open-iconic\\README.md","FileLength":3655,"LastWriteTime":"2025-08-11T17:18:34.9827182+00:00"},"gi4cwoT00EaWLfE9LJLoVWx2\u002Bx/RmJzRTfx678BCt24=":{"Identity":"C:\\Users\\helen\\OneDrive\\Desktop\\Disney_ShowDown\\DisneyShowdown\\wwwroot\\css\\site.css","SourceId":"DisneyShowdown","SourceType":"Discovered","ContentRoot":"C:\\Users\\helen\\OneDrive\\Desktop\\Disney_ShowDown\\DisneyShowdown\\wwwroot\\","BasePath":"_content/DisneyShowdown","RelativePath":"css/site#[.{fingerprint}]?.css","AssetKind":"All","AssetMode":"All","AssetRole":"Primary","AssetMergeBehavior":null,"AssetMergeSource":"","RelatedAsset":null,"AssetTraitName":null,"AssetTraitValue":null,"Fingerprint":"zh9s866nx2","Integrity":"Fx\u002Bc1youNLgejKLBM3S2fD6fcDOSv/D7tNQKm5gws6U=","CopyToOutputDirectory":"Never","CopyToPublishDirectory":"PreserveNewest","OriginalItemSpec":"wwwroot\\css\\site.css","FileLength":2978,"LastWriteTime":"2025-08-11T17:18:34.8881454+00:00"},"jHKAMTm3yb3qjuSh8I392NHPJ4740RvNAsmR0yEv/98=":{"Identity":"C:\\Users\\helen\\OneDrive\\Desktop\\Disney_ShowDown\\DisneyShowdown\\wwwroot\\favicon.png","SourceId":"DisneyShowdown","SourceType":"Discovered","ContentRoot":"C:\\Users\\helen\\OneDrive\\Desktop\\Disney_ShowDown\\DisneyShowdown\\wwwroot\\","BasePath":"_content/DisneyShowdown","RelativePath":"favicon#[.{fingerprint}]?.png","AssetKind":"All","AssetMode":"All","AssetRole":"Primary","AssetMergeBehavior":null,"AssetMergeSource":"","RelatedAsset":null,"AssetTraitName":null,"AssetTraitValue":null,"Fingerprint":"ifv42okdf2","Integrity":"4mWsDy3aHl36ZbGt8zByK7Pvd4kRUoNgTYzRnwmPHwg=","CopyToOutputDirectory":"Never","CopyToPublishDirectory":"PreserveNewest","OriginalItemSpec":"wwwroot\\favicon.png","FileLength":1148,"LastWriteTime":"2025-08-11T17:18:34.9782023+00:00"}},"CachedCopyCandidates":{}}